sbmlxdf/__init__.py
sbmlxdf/_version.py
sbmlxdf/annotation.py
sbmlxdf/compartments.py
sbmlxdf/constraints.py
sbmlxdf/cursor.py
sbmlxdf/events.py
sbmlxdf/fbc.py
sbmlxdf/function_defs.py
sbmlxdf/groups.py
sbmlxdf/init_assign.py
sbmlxdf/misc.py
sbmlxdf/model.py
sbmlxdf/model_attrs.py
sbmlxdf/parameters.py
sbmlxdf/reactions.py
sbmlxdf/rules.py
sbmlxdf/sbase.py
sbmlxdf/sbml_container.py
sbmlxdf/species.py
sbmlxdf/unit_defs.py
sbmlxdf-1.0.3.dist-info/licenses/LICENSE.txt
sbmlxdf-1.0.3.dist-info/METADATA
sbmlxdf-1.0.3.dist-info/WHEEL
sbmlxdf-1.0.3.dist-info/top_level.txt
sbmlxdf-1.0.3.dist-info/RECORD
