Metadata-Version: 2.4
Name: sbmlxdf
Version: 1.0.3
Summary: convert between SBML and tabular structures
Home-page: https://www.cs.hhu.de/lehrstuehle-und-arbeitsgruppen/computational-cell-biology
Author: Peter Schubert
Author-email: peter.schubert@hhu.de
License: GPLv3
Project-URL: Source Code, https://github.com/SchubertP/sbmlxdf
Project-URL: Documentation, https://sbmlxdf.readthedocs.io
Project-URL: Bug Tracker, https://github.com/SchubertP/sbmlxdf/issues
Keywords: systems biology,metabolic modeling,SBML
Classifier: Programming Language :: Python :: 3
Classifier: License :: OSI Approved :: GNU Lesser General Public License v3 (LGPLv3)
Classifier: Operating System :: OS Independent
Classifier: Topic :: Scientific/Engineering :: Bio-Informatics
Requires-Python: >=3.11
License-File: LICENSE.txt
Requires-Dist: pandas>=1.5.0
Requires-Dist: numpy>=1.23.0
Requires-Dist: scipy>=1.13.0
Requires-Dist: openpyxl>=3.0.0
Requires-Dist: python-libsbml-experimental>=5.18.0
Dynamic: author
Dynamic: author-email
Dynamic: classifier
Dynamic: description
Dynamic: description-content-type
Dynamic: home-page
Dynamic: keywords
Dynamic: license
Dynamic: license-file
Dynamic: project-url
Dynamic: requires-dist
Dynamic: requires-python
Dynamic: summary
